colorful_text/__init__.py
colorful_text/colorful.py
colorful_text-0.1.0.dist-info/WHEEL
colorful_text-0.1.0.dist-info/METADATA
colorful_text-0.1.0.dist-info/RECORD
